losswise/__init__.py
losswise/libs.py
losswise/libs2.py
losswise-4.0.dist-info/METADATA
losswise-4.0.dist-info/WHEEL
losswise-4.0.dist-info/top_level.txt
losswise-4.0.dist-info/RECORD
