Metadata-Version: 2.1
Name: losswise
Version: 4.0
Summary: Official Losswise library for Python
Home-page: https://losswise.com
Author: Losswise, Inc.
Author-email: nicodjimenez@gmail.com
License: Apache
Keywords: losswise analytics dashboard deep machine learning tensorflow pytorch optimization ML deep learning
Platform: UNKNOWN
Classifier: Operating System :: OS Independent
Classifier: Programming Language :: Python :: 2
Classifier: Programming Language :: Python :: 3
Requires-Dist: requests (>=2.9.1)
Requires-Dist: six (>=1.9.0)
